etc/securetea/securetea.conf
etc/securetea/antivirus/config.json
etc/securetea/asp/commands.json
etc/securetea/asp/config.json
etc/securetea/log_monitor/server_log/payloads/bad_ua.txt
etc/securetea/log_monitor/server_log/payloads/lfi.txt
etc/securetea/log_monitor/server_log/payloads/port_scan_ua.txt
etc/securetea/log_monitor/server_log/payloads/sqli.txt
etc/securetea/log_monitor/server_log/payloads/web_shell.txt
etc/securetea/log_monitor/server_log/payloads/xss.txt
etc/securetea/log_monitor/server_log/regex/sqli.txt
etc/securetea/log_monitor/server_log/regex/xss.txt
etc/securetea/log_monitor/system_log/harmful_command.txt
etc/securetea/web_deface/path_map.json
securetea/__init__.py
securetea/common.py
securetea/configurations.py
securetea/core.py
securetea/logger.py
securetea/users.py
securetea/args/__init__.py
securetea/args/args_helper.py
securetea/args/arguments.py
securetea/args/config.py
securetea/entry_points/__init__.py
securetea/entry_points/iot_ep.py
securetea/entry_points/securetea_core_ep.py
securetea/entry_points/server_ep.py
securetea/entry_points/system_ep.py
securetea/lib/__init__.py
securetea/lib/antivirus/__init__.py
securetea/lib/antivirus/antivirus_logger.py
securetea/lib/antivirus/core_engine.py
securetea/lib/antivirus/secureTeaAntiVirus.py
securetea/lib/antivirus/cleaner/__init__.py
securetea/lib/antivirus/cleaner/cleaner.py
securetea/lib/antivirus/config/__init__.py
securetea/lib/antivirus/monitor/__init__.py
securetea/lib/antivirus/monitor/monitor_changes.py
securetea/lib/antivirus/monitor/monitor_engine.py
securetea/lib/antivirus/monitor/usb_monitor.py
securetea/lib/antivirus/scanner/__init__.py
securetea/lib/antivirus/scanner/clamav_scanner.py
securetea/lib/antivirus/scanner/hash_scanner.py
securetea/lib/antivirus/scanner/scanner_engine.py
securetea/lib/antivirus/scanner/scanner_parent.py
securetea/lib/antivirus/scanner/virus_total.py
securetea/lib/antivirus/scanner/yara_scanner.py
securetea/lib/antivirus/tools/__init__.py
securetea-2.2.dist-info/LICENSE
securetea-2.2.dist-info/METADATA
securetea-2.2.dist-info/WHEEL
securetea-2.2.dist-info/entry_points.txt
securetea-2.2.dist-info/top_level.txt
securetea-2.2.dist-info/RECORD
