Metadata-Version: 2.1
Name: securetea
Version: 2.2
Summary: SecureTea
Home-page: https://github.com/OWASP/SecureTea-Project
Author: OWASP SecureTea
Author-email: rejah.rehim@owasp.org
License: MIT
Platform: UNKNOWN
Classifier: Development Status :: 4 - Beta
Classifier: Programming Language :: Python
Classifier: Programming Language :: Python :: 2.7
Classifier: Programming Language :: Python :: 3.6
Classifier: Natural Language :: English
Classifier: Topic :: Software Development :: Version Control :: Git
Classifier: Topic :: Software Development :: Testing :: Unit
Requires-Python: >=2.7
Requires-Dist: requests
Requires-Dist: requests-oauthlib
Requires-Dist: py-cpuinfo
Requires-Dist: psutil
Requires-Dist: flask
Requires-Dist: flask-cors
Requires-Dist: pynput
Requires-Dist: python-telegram-bot
Requires-Dist: twilio
Requires-Dist: boto3
Requires-Dist: geocoder
Requires-Dist: pyudev
Requires-Dist: ipwhois
Requires-Dist: future
Requires-Dist: scapy
Requires-Dist: wget
Requires-Dist: bs4
Requires-Dist: shodan
Requires-Dist: NetfilterQueue
Provides-Extra: iot
Requires-Dist: shodan ; extra == 'iot'
Provides-Extra: server
Requires-Dist: pathlib ; extra == 'server'
Requires-Dist: wget ; extra == 'server'
Requires-Dist: yara-python ; extra == 'server'
Requires-Dist: clamd ; extra == 'server'
Requires-Dist: beautifulsoup4 ; extra == 'server'
Requires-Dist: lxml ; extra == 'server'
Provides-Extra: system
Requires-Dist: pathlib ; extra == 'system'
Requires-Dist: wget ; extra == 'system'
Requires-Dist: yara-python ; extra == 'system'
Requires-Dist: clamd ; extra == 'system'
Requires-Dist: beautifulsoup4 ; extra == 'system'
Requires-Dist: lxml ; extra == 'system'
